experiencia5/sonar.v
module sonar (
    input clock,
    input reset,
    input ligar,
    input echo,
    output trigger,
    output pwm,
    output saida_serial,
    output fim_posicao
);



endmodule

experiencia5/sonar_tb.v
`timescale 1ns/1ns

module sonar_tb;

    parameter clockPeriod = 20;
    parameter TEST_TIMER_COUNT = 1_000_000;
    parameter BIT_TIME_NS = 8_680;
    parameter TEST_TIMER_PERIOD_NS = TEST_TIMER_COUNT * clockPeriod;
    parameter TEST_TIMER_TOLERANCE_NS = 5 * clockPeriod;

    // Sinais de entrada
    reg        clock_in = 0;
    reg        reset_in = 0;
    reg        ligar_in = 0;
    reg        echo_in = 0;

    // Sinais de saida
    wire       trigger_out;
    wire       pwm_out;
    wire       saida_serial_out;
    wire       fim_posicao_out;

    // DUT
    sonar #(
        .CONTAGEM_2SEG(TEST_TIMER_COUNT)
    ) dut (
        .clock       (clock_in),
        .reset       (reset_in),
        .ligar       (ligar_in),
        .echo        (echo_in),
        .trigger     (trigger_out),
        .pwm         (pwm_out),
        .saida_serial(saida_serial_out),
        .fim_posicao (fim_posicao_out)
    );

    // Configuracao do clock -> 50 MHz
    always #(clockPeriod/2) clock_in = ~clock_in;

    // Casos de teste e parametros de tempo
    reg [7:0] distancias_cm [0:7];
    reg [11:0] medidas_teste [0:7];
    reg [23:0] angulos_teste [0:7];
    integer caso;
    reg [31:0] larguraPulso;
    integer erros;
    integer trigger_count;
    integer fim_count;
    integer quadros_verificados;
    integer medidas_iniciadas;
    reg trigger_anterior;
    reg verificar_periodo;
    time tempo_medida_anterior;
    time intervalo_medido;

    always @(posedge clock_in) begin
        if ((trigger_out === 1'b1) && !trigger_anterior)
            trigger_count = trigger_count + 1;
        trigger_anterior = (trigger_out === 1'b1);
    end

    always @(posedge fim_posicao_out)
        fim_count = fim_count + 1;

    always @(posedge dut.w_medir) begin
        if (verificar_periodo && medidas_iniciadas > 0) begin
            intervalo_medido = $time - tempo_medida_anterior;
            if (intervalo_medido + TEST_TIMER_TOLERANCE_NS < TEST_TIMER_PERIOD_NS ||
                intervalo_medido > TEST_TIMER_PERIOD_NS + TEST_TIMER_TOLERANCE_NS) begin
                $display("ERRO: intervalo entre medidas foi %0t ns; esperado %0d ns.",
                         intervalo_medido, TEST_TIMER_PERIOD_NS);
                erros = erros + 1;
            end
        end
        tempo_medida_anterior = $time;
        medidas_iniciadas = medidas_iniciadas + 1;
    end

    task verificar_quadro;
        input [6:0] dado_esperado;
        integer bit_index;
        reg paridade_esperada;
        begin
            wait (saida_serial_out === 1'b1);
            wait (saida_serial_out === 1'b0);

            #(BIT_TIME_NS / 2);
            if (saida_serial_out !== 1'b0) begin
                $display("ERRO: bit de start serial invalido.");
                erros = erros + 1;
            end

            for (bit_index = 0; bit_index < 7; bit_index = bit_index + 1) begin
                #(BIT_TIME_NS);
                if (saida_serial_out !== dado_esperado[bit_index]) begin
                    $display("ERRO: dado serial bit %0d=%b, esperado %b (ASCII %h).",
                             bit_index, saida_serial_out, dado_esperado[bit_index], dado_esperado);
                    erros = erros + 1;
                end
            end

            paridade_esperada = ^dado_esperado;
            #(BIT_TIME_NS);
            if (saida_serial_out !== paridade_esperada) begin
                $display("ERRO: paridade serial=%b, esperada %b (ASCII %h).",
                         saida_serial_out, paridade_esperada, dado_esperado);
                erros = erros + 1;
            end

            #(BIT_TIME_NS);
            if (saida_serial_out !== 1'b1) begin
                $display("ERRO: bit de stop serial invalido.");
                erros = erros + 1;
            end
            quadros_verificados = quadros_verificados + 1;
        end
    endtask

    task verificar_parada;
        input integer triggers_esperados;
        input integer fins_esperados;
        begin
            #(TEST_TIMER_PERIOD_NS + 500_000);
            if (trigger_count != triggers_esperados) begin
                $display("ERRO: %0d triggers observados, esperado %0d.",
                         trigger_count, triggers_esperados);
                erros = erros + 1;
            end
            if (fim_count != fins_esperados || fim_posicao_out !== 1'b0) begin
                $display("ERRO: houve fim_posicao durante a interrupcao.");
                erros = erros + 1;
            end
            if (trigger_out !== 1'b0 || saida_serial_out !== 1'b1) begin
                $display("ERRO: trigger ou serial nao retornou ao repouso apos desligar.");
                erros = erros + 1;
            end
        end
    endtask

    // Tarefa para inicializar o sistema
    task reset_dut;
    begin
        ligar_in = 1'b0;
        echo_in  = 1'b0;

        #(2 * clockPeriod);
        reset_in = 1'b1;
        #(2_000); // 2 us
        reset_in = 1'b0;
        @(negedge clock_in);
        #(100_000); // 100 us de espera antes de ligar
    end
    endtask

    // Tarefa para responder autonomamente a um ciclo do Sonar
    task executar_caso;
        input [7:0] distancia_cm;
        input [11:0] medida_esperada;
        input [23:0] angulo_esperado;
        input espera_fim;
        integer caractere;
        reg [6:0] ascii_esperado;
        time inicio_trigger;
        begin
            $display("\nCaso %0d: posicao %03b, distancia %0d cm.", caso, caso[2:0], distancia_cm);

            // 1: Calcula largura do pulso echo em ns
            larguraPulso = distancia_cm * 58_820;

            // 2: Fica à escuta do pulso Trigger gerado pelo Sonar
            wait (trigger_out == 1'b1);
            inicio_trigger = $time;
            wait (trigger_out == 1'b0); // Espera o trigger de 10us terminar

            if (($time - inicio_trigger) != 10_000) begin
                $display("ERRO: trigger durou %0t ns, esperado 10000 ns.", $time - inicio_trigger);
                erros = erros + 1;
            end

            if (dut.fd_sonar.w_endereco !== caso[2:0]) begin
                $display("ERRO: endereco %b, esperado %b.", dut.fd_sonar.w_endereco, caso[2:0]);
                erros = erros + 1;
            end

            // 3: Espera 400 us entre trigger e echo
            #(400_000);

            // 4: Gera pulso echo com largura definida
            echo_in = 1'b1;
            #(larguraPulso);
            echo_in = 1'b0;

            wait (dut.w_pronto_medida == 1'b1);
            #1;
            if (dut.fd_sonar.w_medida !== medida_esperada) begin
                $display("ERRO: caso %0d mediu BCD %h, esperado %h.",
                         caso, dut.fd_sonar.w_medida, medida_esperada);
                erros = erros + 1;
            end

            for (caractere = 0; caractere < 8; caractere = caractere + 1) begin
                case (caractere)
                    0: ascii_esperado = angulo_esperado[22:16];
                    1: ascii_esperado = angulo_esperado[14:8];
                    2: ascii_esperado = angulo_esperado[6:0];
                    3: ascii_esperado = 7'h2C;
                    4: ascii_esperado = {3'b011, medida_esperada[11:8]};
                    5: ascii_esperado = {3'b011, medida_esperada[7:4]};
                    6: ascii_esperado = {3'b011, medida_esperada[3:0]};
                    7: ascii_esperado = 7'h23;
                    default: ascii_esperado = 7'h3F;
                endcase

                wait (dut.w_transmite_serial == 1'b1);
                #1;
                if (dut.fd_sonar.dados_ascii !== ascii_esperado) begin
                    $display("ERRO: caso %0d caractere %0d: ASCII %h, esperado %h.",
                             caso, caractere, dut.fd_sonar.dados_ascii, ascii_esperado);
                    erros = erros + 1;
                end
                verificar_quadro(ascii_esperado);
                wait (dut.w_pronto_serial == 1'b1);
            end

            if (espera_fim) begin
                wait (fim_posicao_out == 1'b1);
                $display("  FIM_POSICAO detectado.");
                wait (fim_posicao_out == 1'b0);
            end else begin
                wait (dut.uc_sonar.Eatual == 4'h7);
            end
        end
    endtask

    task iniciar_medicao;
        begin
            echo_in = 1'b0;
            ligar_in = 1'b1;
            wait (trigger_out == 1'b1);
        end
    endtask

    initial begin
        $display("Inicio da simulacao do Sistema de Sonar");
        
        // Comandos importados da Exp 4 para gerar formas de onda automaticamente
        $dumpfile("sonar.vcd");
        $dumpvars(0, reset_in, ligar_in, echo_in,
                  trigger_out, pwm_out, saida_serial_out, fim_posicao_out);

        // Oito posicoes com larguras de echo coerentes com R=2941 clocks/cm.
        distancias_cm[0] = 100; medidas_teste[0] = 12'h100; angulos_teste[0] = 24'h303230;
        distancias_cm[1] = 74;  medidas_teste[1] = 12'h074; angulos_teste[1] = 24'h303430;
        distancias_cm[2] = 17;  medidas_teste[2] = 12'h017; angulos_teste[2] = 24'h303630;
        distancias_cm[3] = 30;  medidas_teste[3] = 12'h030; angulos_teste[3] = 24'h303830;
        distancias_cm[4] = 80;  medidas_teste[4] = 12'h080; angulos_teste[4] = 24'h313030;
        distancias_cm[5] = 55;  medidas_teste[5] = 12'h055; angulos_teste[5] = 24'h313230;
        distancias_cm[6] = 42;  medidas_teste[6] = 12'h042; angulos_teste[6] = 24'h313430;
        distancias_cm[7] = 12;  medidas_teste[7] = 12'h012; angulos_teste[7] = 24'h313630;
        erros = 0;
        trigger_count = 0;
        fim_count = 0;
        quadros_verificados = 0;
        medidas_iniciadas = 0;
        trigger_anterior = 1'b0;
        verificar_periodo = 1'b0;

        // 1. Reset inicial do sistema
        reset_dut();

        // 2. Aciona o Sonar e verifica uma varredura completa em 20 ms por ciclo.
        verificar_periodo = 1'b1;
        ligar_in = 1'b1;

        for (caso = 0; caso < 8; caso = caso + 1) begin
            executar_caso(distancias_cm[caso], medidas_teste[caso], angulos_teste[caso], 1'b1);
        end

        verificar_periodo = 1'b0;
        if (medidas_iniciadas != 8 || trigger_count != 8 || fim_count != 8 || quadros_verificados != 64) begin
            $display("ERRO: medidas=%0d triggers=%0d fins=%0d quadros=%0d; esperado 8, 8, 8 e 64.",
                     medidas_iniciadas, trigger_count, fim_count, quadros_verificados);
            erros = erros + 1;
        end
        if (dut.fd_sonar.w_endereco !== 3'b000) begin
            $display("ERRO: varredura nao retornou a posicao 000 apos a posicao 111.");
            erros = erros + 1;
        end

        // Interrompe antes do inicio da proxima medida.
        ligar_in = 1'b0;
        verificar_parada(8, 8);

        // Aborta durante o trigger.
        iniciar_medicao();
        #(100);
        ligar_in = 1'b0;
        verificar_parada(9, 8);

        // Aborta enquanto aguarda o echo.
        iniciar_medicao();
        wait (trigger_out == 1'b0);
        ligar_in = 1'b0;
        verificar_parada(10, 8);

        // Aborta durante a contagem de um echo ativo.
        iniciar_medicao();
        wait (trigger_out == 1'b0);
        #(400_000);
        echo_in = 1'b1;
        #(1_000_000);
        ligar_in = 1'b0;
        echo_in = 1'b0;
        verificar_parada(11, 8);

        // Aborta no meio do primeiro quadro serial.
        iniciar_medicao();
        wait (trigger_out == 1'b0);
        #(400_000);
        echo_in = 1'b1;
        #(10 * 58_820);
        echo_in = 1'b0;
        wait (dut.w_transmite_serial == 1'b1);
        wait (saida_serial_out == 1'b0);
        #(3 * BIT_TIME_NS);
        ligar_in = 1'b0;
        verificar_parada(12, 8);

        // Aborta durante a espera pelo proximo intervalo.
        ligar_in = 1'b1;
        caso = 0;
        executar_caso(distancias_cm[0], medidas_teste[0], angulos_teste[0], 1'b0);
        ligar_in = 1'b0;
        verificar_parada(13, 8);

        // A parada deve manter o ultimo endereco comandado ao servomotor.
        ligar_in = 1'b1;
        executar_caso(distancias_cm[0], medidas_teste[0], angulos_teste[0], 1'b1);
        ligar_in = 1'b0;
        verificar_parada(14, 9);
        if (dut.fd_sonar.w_endereco !== 3'b001) begin
            $display("ERRO: endereco do servo mudou apos desligar; esperado 001.");
            erros = erros + 1;
        end
        if (quadros_verificados != 80) begin
            $display("ERRO: %0d quadros 7E1 verificados, esperado 80.", quadros_verificados);
            erros = erros + 1;
        end

        if (erros == 0)
            $display("\nPASSOU: varredura, periodo, distancias, 7E1 e cancelamentos verificados.");
        else
            $display("\nFALHOU: %0d verificacao(oes) com erro.", erros);

        $display("Fim da simulacao do Sistema de Sonar");
        $dumpoff;
        $finish;
    end

    initial begin
        #500_000_000;
        $display("FALHOU: timeout aguardando algum evento do sistema.");
        $finish;
    end

endmodule

experiencia5/sonar.vcd
$date
	Tue Sep 29 05:47:28 2026
$end
$version
	ModelSim Version 10.5b
$end
$timescale
	1ns
$end

$scope module sonar_tb $end
$var reg 1 ! reset_in $end
$var reg 1 " ligar_in $end
$var reg 1 # echo_in $end
$var wire 1 $ trigger_out $end
$var wire 1 % pwm_out $end
$var wire 1 & saida_serial_out $end
$var wire 1 ' fim_posicao_out $end
$upscope $end
$enddefinitions $end
#0
$dumpvars
0!
0"
0#
0$
x%
1&
0'
$end
#40
1!
0%
#2040
0!
#2050
1%
#102040
1"
#102110
1$
#112110
0$
#512110
1#
#702050
0%
#6394110
0#
#6402930
0&
#6446330
1&
#6463690
0&
#6481050
1&
#6498530
0&
#6515890
1&
#6524570
0&
#6541930
1&
#6559290
0&
#6567970
1&
#6594130
0&
#6637530
1&
#6654890
0&
#6672250
1&
#6689730
0&
#6715770
1&
#6733130
0&
#6741810
1&
#6750490
0&
#6759170
1&
#6785330
0&
#6794010
1&
#6802690
0&
#6828730
1&
#6846090
0&
#6854770
1&
#6880930
0&
#6924330
1&
#6941690
0&
#6959050
1&
#6976530
0&
#7019930
1&
#7037290
0&
#7054650
1&
#7072130
0&
#7080810
1&
#7098170
0&
#7124210
1&
#7132890
0&
#7141570
1&
#20002050
1%
#20102050
1'
#20102070
0'
#20102150
1$
#20112150
0$
#20512150
1#
#20702050
0%
#24864830
0#
#24873650
0&
#24917050
1&
#24934410
0&
#24951770
1&
#24969250
0&
#24995290
1&
#25003970
0&
#25012650
1&
#25030010
0&
#25038690
1&
#25064850
0&
#25108250
1&
#25125610
0&
#25142970
1&
#25160450
0&
#25186490
1&
#25203850
0&
#25212530
1&
#25221210
0&
#25229890
1&
#25256050
0&
#25299450
1&
#25316810
0&
#25334170
1&
#25351650
0&
#25360330
1&
#25386370
0&
#25395050
1&
#25412410
0&
#25421090
1&
#25447250
0&
#25473290
1&
#25481970
0&
#25490650
1&
#25508010
0&
#25516690
1&
#25542850
0&
#25551530
1&
#25568890
0&
#25594930
1&
#25603610
0&
#25612290
1&
#40002050
1%
#40102070
1'
#40102090
0'
#40102170
1$
#40112170
0$
#40512170
1#
#40916050
0%
#41512110
0#
#41520930
0&
#41564330
1&
#41581690
0&
#41599050
1&
#41616530
0&
#41633890
1&
#41651250
0&
#41659930
1&
#41677290
0&
#41694650
1&
#41712130
0&
#41755530
1&
#41772890
0&
#41790250
1&
#41807730
0&
#41833770
1&
#41851130
0&
#41859810
1&
#41868490
0&
#41877170
1&
#41903330
0&
#41946730
1&
#41964090
0&
#41981450
1&
#41998930
0&
#42007610
1&
#42016290
0&
#42042330
1&
#42059690
0&
#42068370
1&
#42094530
0&
#42103210
1&
#42129250
0&
#42137930
1&
#42155290
0&
#42163970
1&
#42190130
0&
#42198810
1&
#42216170
0&
#42242210
1&
#42250890
0&
#42259570
1&
#60002050
1%
#60102090
1'
#60102110
0'
#60102190
1$
#60112190
0$
#60512190
1#
#61131050
0%
#62276790
0#
#62285610
0&
#62329010
1&
#62346370
0&
#62363730
1&
#62381210
0&
#62415930
1&
#62441970
0&
#62450650
1&
#62476810
0&
#62520210
1&
#62537570
0&
#62554930
1&
#62572410
0&
#62598450
1&
#62615810
0&
#62624490
1&
#62633170
0&
#62641850
1&
#62668010
0&
#62711410
1&
#62728770
0&
#62746130
1&
#62763610
0&
#62772290
1&
#62789650
0&
#62807010
1&
#62824370
0&
#62841730
1&
#62859210
0&
#62902610
1&
#62919970
0&
#62937330
1&
#62954810
0&
#62963490
1&
#62980850
0&
#63006890
1&
#63015570
0&
#63024250
1&
#80002050
1%
#80102110
1'
#80102130
0'
#80102210
1$
#80112210
0$
#80512210
1#
#81345050
0%
#85217810
0#
#85226630
0&
#85235310
1&
#85243990
0&
#85270030
1&
#85287390
0&
#85296070
1&
#85322230
0&
#85365630
1&
#85382990
0&
#85400350
1&
#85417830
0&
#85461230
1&
#85478590
0&
#85495950
1&
#85513430
0&
#85539470
1&
#85556830
0&
#85565510
1&
#85574190
0&
#85582870
1&
#85609030
0&
#85652430
1&
#85669790
0&
#85687150
1&
#85704630
0&
#85739350
1&
#85765390
0&
#85774070
1&
#85800230
0&
#85843630
1&
#85860990
0&
#85878350
1&
#85895830
0&
#85904510
1&
#85921870
0&
#85947910
1&
#85956590
0&
#85965270
1&
#100002050
1%
#100102130
1'
#100102150
0'
#100102230
1$
#100112230
0$
#100512230
1#
#101559050
0%
#103747330
0#
#103756150
0&
#103764830
1&
#103773510
0&
#103799550
1&
#103816910
0&
#103825590
1&
#103851750
0&
#103869110
1&
#103877790
0&
#103895150
1&
#103912510
0&
#103921190
1&
#103947350
0&
#103990750
1&
#104008110
0&
#104025470
1&
#104042950
0&
#104068990
1&
#104086350
0&
#104095030
1&
#104103710
0&
#104112390
1&
#104138550
0&
#104181950
1&
#104199310
0&
#104216670
1&
#104234150
0&
#104242830
1&
#104251510
0&
#104260190
1&
#104268870
0&
#104277550
1&
#104294910
0&
#104312270
1&
#104329750
0&
#104338430
1&
#